fescache/__init__.py
fescache/_base.py
fescache/aio_rdbclient.py
fescache/err.py
fescache/rdbclient.py
fescache/utils.py
fescache-1.1.3.dist-info/LICENSE
fescache-1.1.3.dist-info/METADATA
fescache-1.1.3.dist-info/WHEEL
fescache-1.1.3.dist-info/top_level.txt
fescache-1.1.3.dist-info/RECORD
